{
	"info": {
		"_postman_id": "bd92e4c3-3042-45e9-963f-10061dd40028",
		"name": "RestDemo1",
		"schema": "https://schema.getpostman.com/json/collection/v2.1.0/collection.json",
		"_exporter_id": "29597461"
	},
	"item": [
		{
			"name": "Get all books data",
			"request": {
				"method": "GET",
				"header": [],
				"url": {
					"raw": "http://127.0.0.1:8000/libraryapi/books/",
					"protocol": "http",
					"host": [
						"127",
						"0",
						"0",
						"1"
					],
					"port": "8000",
					"path": [
						"libraryapi",
						"books",
						""
					]
				}
			},
			"response": []
		},
		{
			"name": "Delete book data",
			"request": {
				"method": "DELETE",
				"header": [],
				"url": {
					"raw": "http://127.0.0.1:8000/libraryapi/books/4/",
					"protocol": "http",
					"host": [
						"127",
						"0",
						"0",
						"1"
					],
					"port": "8000",
					"path": [
						"libraryapi",
						"books",
						"4",
						""
					]
				}
			},
			"response": []
		},
		{
			"name": "Update book data",
			"request": {
				"method": "PUT",
				"header": [],
				"body": {
					"mode": "raw",
					"raw": "{\n    \"bookTitle\": \"Think like a monk\",\n    \"bookAuthor\": \"Jay Shetty\",\n    \"bookPrice\": \"350\"\n}",
					"options": {
						"raw": {
							"language": "json"
						}
					}
				},
				"url": {
					"raw": "http://127.0.0.1:8000/libraryapi/books/2/",
					"protocol": "http",
					"host": [
						"127",
						"0",
						"0",
						"1"
					],
					"port": "8000",
					"path": [
						"libraryapi",
						"books",
						"2",
						""
					]
				}
			},
			"response": []
		},
		{
			"name": "Add new book data",
			"request": {
				"method": "POST",
				"header": [],
				"body": {
					"mode": "raw",
					"raw": "{\n    \"bookTitle\": \"Merchant of Venice\",\n    \"bookAuthor\": \"William Shakespeare\",\n    \"bookPrice\": \"150\"\n}",
					"options": {
						"raw": {
							"language": "json"
						}
					}
				},
				"url": {
					"raw": "http://127.0.0.1:8000/libraryapi/books/",
					"protocol": "http",
					"host": [
						"127",
						"0",
						"0",
						"1"
					],
					"port": "8000",
					"path": [
						"libraryapi",
						"books",
						""
					]
				}
			},
			"response": []
		}
	]
}